diavgeia_api/__init__.py
diavgeia_api/_config.py
diavgeia_api/client.py
diavgeia_api/exceptions.py
diavgeia_api/models/__init__.py
diavgeia_api/models/decisions.py
diavgeia_api/models/dictionaries.py
diavgeia_api/models/organizations.py
diavgeia_api/models/search.py
diavgeia_api/models/types.py
diavgeia_api/utils.py
diavgeia_api-0.0.4.dist-info/LICENSE
diavgeia_api-0.0.4.dist-info/METADATA
diavgeia_api-0.0.4.dist-info/WHEEL
diavgeia_api-0.0.4.dist-info/RECORD
