Metadata-Version: 2.3
Name: diavgeia-api
Version: 0.0.4
Summary: Python wrapper for the Diavgeia Open Data API
License: MIT
Author: Konstantinos Voulgaropoulos
Author-email: voulkon93@gmail.com
Requires-Python: >=3.9,<4.0
Classifier: License :: OSI Approved :: MIT License
Classifier: Programming Language :: Python :: 3
Classifier: Programming Language :: Python :: 3.9
Classifier: Programming Language :: Python :: 3.10
Classifier: Programming Language :: Python :: 3.11
Classifier: Programming Language :: Python :: 3.12
Classifier: Programming Language :: Python :: 3.13
Provides-Extra: dev
Requires-Dist: loguru (>=0.7.2,<0.8.0)
Requires-Dist: pydantic (>=2.7.0,<3.0.0)
Requires-Dist: requests (>=2.31.0,<3.0.0)
